Cheetah/CacheRegion.py
Cheetah/CacheStore.py
Cheetah/CheetahWrapper.py
Cheetah/Compiler.py
Cheetah/DirectiveAnalyzer.py
Cheetah/Django.py
Cheetah/DummyTransaction.py
Cheetah/ErrorCatchers.py
Cheetah/FileUtils.py
Cheetah/Filters.py
Cheetah/ImportHooks.py
Cheetah/ImportManager.py
Cheetah/LoadTemplate.py
Cheetah/NameMapper.py
Cheetah/Parser.py
Cheetah/Servlet.py
Cheetah/SettingsManager.py
Cheetah/SourceReader.py
Cheetah/Template.py
Cheetah/TemplateCmdLineIface.py
Cheetah/Unspecified.py
Cheetah/Version.py
Cheetah/__init__.py
Cheetah/_namemapper.cp36-win_amd64.pyd
Cheetah/compat.py
Cheetah/convertTmplPathToModuleName.py
Cheetah/Macros/I18n.py
Cheetah/Macros/__init__.py
Cheetah/Templates/SkeletonPage.py
Cheetah/Templates/SkeletonPage.tmpl
Cheetah/Templates/_SkeletonPage.py
Cheetah/Templates/__init__.py
Cheetah/Tests/Analyzer.py
Cheetah/Tests/Boinker.py
Cheetah/Tests/CheetahWrapper.py
Cheetah/Tests/Cheps.py
Cheetah/Tests/Filters.py
Cheetah/Tests/ImportHooks.py
Cheetah/Tests/LoadTemplate.py
Cheetah/Tests/Misc.py
Cheetah/Tests/NameMapper.py
Cheetah/Tests/Parser.py
Cheetah/Tests/Performance.py
Cheetah/Tests/Pinger.py
Cheetah/Tests/Regressions.py
Cheetah/Tests/SyntaxAndOutput.py
Cheetah/Tests/Template.py
Cheetah/Tests/TemplateCmdLineIface.py
Cheetah/Tests/Test.py
Cheetah/Tests/Unicode.py
Cheetah/Tests/__init__.py
Cheetah/Tests/test_abs_import.py
Cheetah/Tests/xmlrunner.py
Cheetah/Tests/ImportHooksTemplates/index.tmpl
Cheetah/Tests/ImportHooksTemplates/layout.tmpl
Cheetah/Tools/CGITemplate.py
Cheetah/Tools/MondoReport.py
Cheetah/Tools/MondoReportDoc.txt
Cheetah/Tools/RecursiveNull.py
Cheetah/Tools/SiteHierarchy.py
Cheetah/Tools/__init__.py
Cheetah/Utils/Indenter.py
Cheetah/Utils/Misc.py
Cheetah/Utils/WebInputMixin.py
Cheetah/Utils/__init__.py
Cheetah/Utils/htmlDecode.py
Cheetah/Utils/htmlEncode.py
Cheetah/Utils/statprof.py
CT3-3.4.0.dist-info/LICENSE
CT3-3.4.0.dist-info/METADATA
CT3-3.4.0.dist-info/WHEEL
CT3-3.4.0.dist-info/entry_points.txt
CT3-3.4.0.dist-info/top_level.txt
CT3-3.4.0.dist-info/RECORD
